[
    {
        "NAME": "Anemia",
        "ICON": "",
        "TIER": 1,
        "DES": "",
        "ING1": "Nettle",
        "TEMP1": "None (Default)",
        "ING2": "Dandelion",
        "TEMP2": "None (Default)",
        "ING3": "Spinach",
        "TEMP3": "None (Default)",
        "SYMP1": "cold hands and feet",
        "SYMP2": "weak muscles",
        "COMP": ""
    },
    {
        "NAME": "Beriberi",
        "ICON": "",
        "TIER": 1,
        "DES": "",
        "ING1": "Fenugreek",
        "TEMP1": "Hot",
        "ING2": "Molasses",
        "TEMP2": "Hot",
        "ING3": "Ginkgo",
        "TEMP3": "Hot",
        "SYMP1": "rapid heartbeat",
        "SYMP2": "weak muscles",
        "COMP": ""
    },
    {
        "NAME": "Common Cold",
        "ICON": "",
        "TIER": 1,
        "DES": "",
        "ING1": "Elderberry",
        "TEMP1": "Hot",
        "ING2": "Echinacea",
        "TEMP2": "Hot",
        "ING3": "Honey",
        "TEMP3": "Hot",
        "SYMP1": "congested sinuses",
        "SYMP2": "fever and chills",
        "COMP": ""
    },
    {
        "NAME": "Digestive Problems",
        "ICON": "",
        "TIER": 1,
        "DES": "",
        "ING1": "Ginger",
        "TEMP1": "None (Default)",
        "ING2": "Peppermint",
        "TEMP2": "None (Default)",
        "ING3": "Prunes",
        "TEMP3": "None (Default)",
        "SYMP1": "abdominal pain",
        "SYMP2": "bloating",
        "COMP": ""
    },
    {
        "NAME": "Xerophthalmia",
        "ICON": "",
        "TIER": 1,
        "DES": "",
        "ING1": "Elderberry",
        "TEMP1": "Cold",
        "ING2": "Rose Hips",
        "TEMP2": "Cold",
        "ING3": "Milk Thistle",
        "TEMP3": "Cold",
        "SYMP1": "dry eyes",
        "SYMP2": "difficulty seeing at night",
        "COMP": ""
    },
    {
        "NAME": "Ear Infection",
        "ICON": "",
        "TIER": 1,
        "DES": "",
        "ING1": "Garlic",
        "TEMP1": "Hot",
        "ING2": "Olive Oil",
        "TEMP2": "Hot",
        "ING3": "Echinacea",
        "TEMP3": "Hot",
        "SYMP1": "ear pain",
        "SYMP2": "hearing loss",
        "COMP": ""
    },
    {
        "NAME": "Eczema",
        "ICON": "",
        "TIER": 1,
        "DES": "",
        "ING1": "Calendula",
        "TEMP1": "None (Default)",
        "ING2": "Aloe Vera",
        "TEMP2": "None (Default)",
        "ING3": "Oatmeal",
        "TEMP3": "None (Default)",
        "SYMP1": "dry skin",
        "SYMP2": "rash",
        "COMP": ""
    },
    {
        "NAME": "Fatigue",
        "ICON": "",
        "TIER": 1,
        "DES": "",
        "ING1": "Echinacea",
        "TEMP1": "Hot",
        "ING2": "Spinach",
        "TEMP2": "Hot",
        "ING3": "Ginseng",
        "TEMP3": "Hot",
        "SYMP1": "lack of energy",
        "SYMP2": "weak muscles",
        "COMP": ""
    },
    {
        "NAME": "Insomnia",
        "ICON": "",
        "TIER": 1,
        "DES": "",
        "ING1": "Ginkgo",
        "TEMP1": "Hot",
        "ING2": "Chamomile",
        "TEMP2": "Hot",
        "ING3": "St. John's Wort",
        "TEMP3": "Hot",
        "SYMP1": "difficulty sleeping",
        "SYMP2": "poor concentration",
        "COMP": ""
    },
    {
        "NAME": "Migraine",
        "ICON": "",
        "TIER": 1,
        "DES": "",
        "ING1": "Peppermint",
        "TEMP1": "Hot",
        "ING2": "Green Tea",
        "TEMP2": "Hot",
        "ING3": "Chamomile",
        "TEMP3": "Hot",
        "SYMP1": "headache",
        "SYMP2": "blurred vision",
        "COMP": ""
    },
    {
        "NAME": "Mind Fog",
        "ICON": "",
        "TIER": 1,
        "DES": "",
        "ING1": "Ginkgo",
        "TEMP1": "None (Default)",
        "ING2": "Ginseng",
        "TEMP2": "None (Default)",
        "ING3": "St. John's Wort",
        "TEMP3": "None (Default)",
        "SYMP1": "poor concentration",
        "SYMP2": "irritability",
        "COMP": ""
    },
    {
        "NAME": "Hypocalcemia",
        "ICON": "",
        "TIER": 1,
        "DES": "",
        "ING1": "Magnesium",
        "TEMP1": "Hot",
        "ING2": "Willow Bark",
        "TEMP2": "Hot",
        "ING3": "Chamomile",
        "TEMP3": "Hot",
        "SYMP1": "muscle cramps",
        "SYMP2": "numbness in extremeties",
        "COMP": ""
    },
    {
        "NAME": "Nausea",
        "ICON": "",
        "TIER": 1,
        "DES": "",
        "ING1": "Ginger",
        "TEMP1": "Cold",
        "ING2": "Lemon",
        "TEMP2": "Cold",
        "ING3": "Peppermint",
        "TEMP3": "Cold",
        "SYMP1": "dizziness",
        "SYMP2": "loss of appetite",
        "COMP": ""
    },
    {
        "NAME": "Hypovitaminosis A",
        "ICON": "",
        "TIER": 1,
        "DES": "",
        "ING1": "Spinach",
        "TEMP1": "None (Default)",
        "ING2": "Milk Thistle",
        "TEMP2": "None (Default)",
        "ING3": "Olive Oil",
        "TEMP3": "None (Default)",
        "SYMP1": "dry skin",
        "SYMP2": "difficulty seeing at night",
        "COMP": ""
    },
    {
        "NAME": "Pellagra",
        "ICON": "",
        "TIER": 1,
        "DES": "",
        "ING1": "Willow Bark",
        "TEMP1": "Cold",
        "ING2": "Ginseng",
        "TEMP2": "Cold",
        "ING3": "Oatmeal",
        "TEMP3": "Cold",
        "SYMP1": "rash",
        "SYMP2": "numbness in extremeties",
        "COMP": ""
    },
    {
        "NAME": "Rickets",
        "ICON": "",
        "TIER": 1,
        "DES": "",
        "ING1": "Nettle",
        "TEMP1": "None (Default)",
        "ING2": "Magnesium",
        "TEMP2": "None (Default)",
        "ING3": "Milk Thistle",
        "TEMP3": "None (Default)",
        "SYMP1": "muscle cramps",
        "SYMP2": "weak muscles",
        "COMP": ""
    },
    {
        "NAME": "Scurvy",
        "ICON": "",
        "TIER": 1,
        "DES": "",
        "ING1": "Lemon",
        "TEMP1": "Cold",
        "ING2": "Orange",
        "TEMP2": "Cold",
        "ING3": "Rose Hips",
        "TEMP3": "Cold",
        "SYMP1": "swelling",
        "SYMP2": "bleeding gums",
        "COMP": ""
    },
    {
        "NAME": "Kwashiorkor",
        "ICON": "",
        "TIER": 1,
        "DES": "",
        "ING1": "Peppermint",
        "TEMP1": "None (Default)",
        "ING2": "Prunes",
        "TEMP2": "None (Default)",
        "ING3": "Nettle",
        "TEMP3": "None (Default)",
        "SYMP1": "bloating",
        "SYMP2": "swelling",
        "COMP": ""
    },
    {
        "NAME": "Toothache",
        "ICON": "",
        "TIER": 1,
        "DES": "",
        "ING1": "Clove",
        "TEMP1": "Hot",
        "ING2": "Chamomile",
        "TEMP2": "Hot",
        "ING3": "Salt",
        "TEMP3": "Hot",
        "SYMP1": "headache",
        "SYMP2": "bleeding gums",
        "COMP": ""
    },
    {
        "NAME": "Marasmus",
        "ICON": "",
        "TIER": 1,
        "DES": "",
        "ING1": "Oatmeal",
        "TEMP1": "Hot",
        "ING2": "Ginseng",
        "TEMP2": "Hot",
        "ING3": "Molasses",
        "TEMP3": "Hot",
        "SYMP1": "weight loss",
        "SYMP2": "lack of energy",
        "COMP": ""
    },
    {
        "NAME": "Weak Immune System",
        "ICON": "",
        "TIER": 1,
        "DES": "",
        "ING1": "Reishi",
        "TEMP1": "None (Default)",
        "ING2": "Garlic",
        "TEMP2": "None (Default)",
        "ING3": "Echinacea",
        "TEMP3": "None (Default)",
        "SYMP1": "slow to heal",
        "SYMP2": "lack of energy",
        "COMP": ""
    },
    {
        "NAME": "Arthritis",
        "ICON": "",
        "TIER": 2,
        "DES": "",
        "ING1": "Ginger",
        "TEMP1": "None (Default)",
        "ING2": "Dandelion",
        "TEMP2": "None (Default)",
        "ING3": "Alfalfa",
        "TEMP3": "Cold",
        "SYMP1": "swelling",
        "SYMP2": "stiff joints",
        "COMP": ""
    },
    {
        "NAME": "Bronchitis",
        "ICON": "",
        "TIER": 2,
        "DES": "",
        "ING1": "Eucalyptus",
        "TEMP1": "None (Default)",
        "ING2": "Hawthorn",
        "TEMP2": "Hot",
        "ING3": "Thyme",
        "TEMP3": "Hot",
        "SYMP1": "cough",
        "SYMP2": "strained breathing",
        "COMP": ""
    },
    {
        "NAME": "Sinus Infection",
        "ICON": "",
        "TIER": 2,
        "DES": "",
        "ING1": "Goldenseal",
        "TEMP1": "Cold",
        "ING2": "Eucalyptus",
        "TEMP2": "Hot",
        "ING3": "Elderflower",
        "TEMP3": "Hot",
        "SYMP1": "congested sinuses",
        "SYMP2": "sinus pain",
        "COMP": ""
    },
    {
        "NAME": "Constipation",
        "ICON": "",
        "TIER": 2,
        "DES": "",
        "ING1": "Flax Seeds",
        "TEMP1": "None (Default)",
        "ING2": "Prunes",
        "TEMP2": "Hot",
        "ING3": "Water",
        "TEMP3": "Hot",
        "SYMP1": "abdominal pain",
        "SYMP2": "bloating",
        "COMP": ""
    },
    {
        "NAME": "Dehydration",
        "ICON": "",
        "TIER": 2,
        "DES": "",
        "ING1": "Water",
        "TEMP1": "Cold",
        "ING2": "Lemon",
        "TEMP2": "None (Default)",
        "ING3": "Willow Bark",
        "TEMP3": "Cold",
        "SYMP1": "increased thirst",
        "SYMP2": "muscle cramps",
        "COMP": ""
    },
    {
        "NAME": "Depression",
        "ICON": "",
        "TIER": 2,
        "DES": "",
        "ING1": "St. John's Wort",
        "TEMP1": "None (Default)",
        "ING2": "Lavender",
        "TEMP2": "Hot",
        "ING3": "Reishi",
        "TEMP3": "None (Default)",
        "SYMP1": "low mood",
        "SYMP2": "difficulty sleeping",
        "COMP": ""
    },
    {
        "NAME": "Flu",
        "ICON": "",
        "TIER": 2,
        "DES": "",
        "ING1": "Lemon",
        "TEMP1": "Hot",
        "ING2": "Elderberry",
        "TEMP2": "None (Default)",
        "ING3": "Echinacea",
        "TEMP3": "Hot",
        "SYMP1": "fever and chills",
        "SYMP2": "muscle cramps",
        "COMP": ""
    },
    {
        "NAME": "Gout",
        "ICON": "",
        "TIER": 2,
        "DES": "",
        "ING1": "Cherry",
        "TEMP1": "Cold",
        "ING2": "Alfalfa",
        "TEMP2": "Cold",
        "ING3": "Turmeric",
        "TEMP3": "None (Default)",
        "SYMP1": "joint pain",
        "SYMP2": "swelling",
        "COMP": ""
    },
    {
        "NAME": "Hay Fever",
        "ICON": "",
        "TIER": 2,
        "DES": "",
        "ING1": "Elderflower",
        "TEMP1": "None (Default)",
        "ING2": "Goldenseal",
        "TEMP2": "Hot",
        "ING3": "Echinacea",
        "TEMP3": "None (Default)",
        "SYMP1": "sneezing",
        "SYMP2": "congested sinuses",
        "COMP": ""
    },
    {
        "NAME": "Hives",
        "ICON": "",
        "TIER": 2,
        "DES": "",
        "ING1": "Oatmeal",
        "TEMP1": "Cold",
        "ING2": "Chamomile",
        "TEMP2": "Cold",
        "ING3": "Calendula",
        "TEMP3": "None (Default)",
        "SYMP1": "rash",
        "SYMP2": "itchy skin",
        "COMP": ""
    },
    {
        "NAME": "Osteoporosis",
        "ICON": "",
        "TIER": 2,
        "DES": "",
        "ING1": "Pomegranate",
        "TEMP1": "None (Default)",
        "ING2": "Alfalfa",
        "TEMP2": "Cold",
        "ING3": "Red Clover",
        "TEMP3": "None (Default)",
        "SYMP1": "back pain",
        "SYMP2": "bruising",
        "COMP": ""
    },
    {
        "NAME": "Pneumonia",
        "ICON": "",
        "TIER": 2,
        "DES": "",
        "ING1": "Eucalyptus",
        "TEMP1": "Hot",
        "ING2": "Thyme",
        "TEMP2": "Hot",
        "ING3": "Hawthorn",
        "TEMP3": "None (Default)",
        "SYMP1": "strained breathing",
        "SYMP2": "wheezing",
        "COMP": ""
    },
    {
        "NAME": "Psoriasis",
        "ICON": "",
        "TIER": 2,
        "DES": "",
        "ING1": "Lemon Balm",
        "TEMP1": "None (Default)",
        "ING2": "Aloe Vera",
        "TEMP2": "Cold",
        "ING3": "Calendula",
        "TEMP3": "None (Default)",
        "SYMP1": "dry skin",
        "SYMP2": "itchy skin",
        "COMP": ""
    },
    {
        "NAME": "Sciatica",
        "ICON": "",
        "TIER": 2,
        "DES": "",
        "ING1": "Turmeric",
        "TEMP1": "None (Default)",
        "ING2": "Ginseng",
        "TEMP2": "Hot",
        "ING3": "Willow Bark",
        "TEMP3": "Hot",
        "SYMP1": "back pain",
        "SYMP2": "numbness in extremeties",
        "COMP": ""
    },
    {
        "NAME": "Tinnitus",
        "ICON": "",
        "TIER": 2,
        "DES": "",
        "ING1": "Ginkgo",
        "TEMP1": "Hot",
        "ING2": "Green Tea",
        "TEMP2": "None (Default)",
        "ING3": "Lemon",
        "TEMP3": "Hot",
        "SYMP1": "ringing in ears",
        "SYMP2": "poor concentration",
        "COMP": ""
    },
    {
        "NAME": "Tonsillitis",
        "ICON": "",
        "TIER": 2,
        "DES": "",
        "ING1": "Water",
        "TEMP1": "Hot",
        "ING2": "Salt",
        "TEMP2": "Hot",
        "ING3": "Honey",
        "TEMP3": "None (Default)",
        "SYMP1": "sore throat",
        "SYMP2": "fever and chills",
        "COMP": ""
    },
    {
        "NAME": "Urinary Tract Infection",
        "ICON": "",
        "TIER": 2,
        "DES": "",
        "ING1": "Cranberry",
        "TEMP1": "None (Default)",
        "ING2": "Fenugreek",
        "TEMP2": "None (Default)",
        "ING3": "Water",
        "TEMP3": "Cold",
        "SYMP1": "pelvic pain",
        "SYMP2": "fever and chills",
        "COMP": ""
    },
    {
        "NAME": "Vertigo",
        "ICON": "",
        "TIER": 2,
        "DES": "",
        "ING1": "Ginger",
        "TEMP1": "Cold",
        "ING2": "Peppermint",
        "TEMP2": "Cold",
        "ING3": "Ginkgo",
        "TEMP3": "None (Default)",
        "SYMP1": "ringing in ears",
        "SYMP2": "nausea",
        "COMP": ""
    },
    {
        "NAME": "Acne",
        "ICON": "",
        "TIER": 3,
        "DES": "",
        "ING1": "Tea Tree Oil",
        "TEMP1": "None (Default)",
        "ING2": "Guggul",
        "TEMP2": "None (Default)",
        "ING3": "Licorice Root",
        "TEMP3": "Hot",
        "SYMP1": "cysts",
        "SYMP2": "rash",
        "COMP": ""
    },
    {
        "NAME": "Alopecia",
        "ICON": "",
        "TIER": 3,
        "DES": "",
        "ING1": "Rosemary",
        "TEMP1": "Hot",
        "ING2": "Lemon Balm",
        "TEMP2": "Cold",
        "ING3": "Tea Tree Oil",
        "TEMP3": "None (Default)",
        "SYMP1": "hair loss",
        "SYMP2": "itchy skin",
        "COMP": ""
    },
    {
        "NAME": "Asthma",
        "ICON": "",
        "TIER": 3,
        "DES": "",
        "ING1": "Eucalyptus",
        "TEMP1": "Hot",
        "ING2": "Clove",
        "TEMP2": "None (Default)",
        "ING3": "Hawthorn",
        "TEMP3": "Cold",
        "SYMP1": "wheezing",
        "SYMP2": "chest pain",
        "COMP": ""
    },
    {
        "NAME": "Carpal Tunnel Syndrome",
        "ICON": "",
        "TIER": 3,
        "DES": "",
        "ING1": "Arnica",
        "TEMP1": "None (Default)",
        "ING2": "Willow Bark",
        "TEMP2": "Hot",
        "ING3": "Bitter Melon",
        "TEMP3": "Hot",
        "SYMP1": "joint pain",
        "SYMP2": "numbness in extremeties",
        "COMP": ""
    },
    {
        "NAME": "Celiac Disease",
        "ICON": "",
        "TIER": 3,
        "DES": "",
        "ING1": "Slippery Elm",
        "TEMP1": "Hot",
        "ING2": "Marshmallow Root",
        "TEMP2": "None (Default)",
        "ING3": "Cinnamon",
        "TEMP3": "Cold",
        "SYMP1": "gas",
        "SYMP2": "weight loss",
        "COMP": ""
    },
    {
        "NAME": "Food Poisoning",
        "ICON": "",
        "TIER": 3,
        "DES": "",
        "ING1": "Charcoal",
        "TEMP1": "None (Default)",
        "ING2": "Fenugreek",
        "TEMP2": "None (Default)",
        "ING3": "Peppermint",
        "TEMP3": "Cold",
        "SYMP1": "nausea",
        "SYMP2": "vomiting",
        "COMP": ""
    },
    {
        "NAME": "High Blood Pressure",
        "ICON": "",
        "TIER": 3,
        "DES": "",
        "ING1": "Fish Oil",
        "TEMP1": "None (Default)",
        "ING2": "Hawthorn",
        "TEMP2": "Hot",
        "ING3": "Bugleweed",
        "TEMP3": "None (Default)",
        "SYMP1": "chest pain",
        "SYMP2": "strained breathing",
        "COMP": ""
    },
    {
        "NAME": "Hyperglycemia",
        "ICON": "",
        "TIER": 3,
        "DES": "",
        "ING1": "Bitter Melon",
        "TEMP1": "Cold",
        "ING2": "Aloe Vera",
        "TEMP2": "Cold",
        "ING3": "Cinnamon",
        "TEMP3": "None (Default)",
        "SYMP1": "increased thirst",
        "SYMP2": "nausea",
        "COMP": ""
    },
    {
        "NAME": "Hyperthyroidism",
        "ICON": "",
        "TIER": 3,
        "DES": "",
        "ING1": "Bugleweed",
        "TEMP1": "Cold",
        "ING2": "Lemon Balm",
        "TEMP2": "None (Default)",
        "ING3": "Motherwort",
        "TEMP3": "Hot",
        "SYMP1": "weight loss",
        "SYMP2": "irregular heartbeat",
        "COMP": ""
    },
    {
        "NAME": "Hypoglycemia",
        "ICON": "",
        "TIER": 3,
        "DES": "",
        "ING1": "Licorice Root",
        "TEMP1": "None (Default)",
        "ING2": "Cinnamon",
        "TEMP2": "Hot",
        "ING3": "Lemon Balm",
        "TEMP3": "Hot",
        "SYMP1": "nausea",
        "SYMP2": "irregular heartbeat",
        "COMP": ""
    },
    {
        "NAME": "Hypothyroidism",
        "ICON": "",
        "TIER": 3,
        "DES": "",
        "ING1": "Kelp",
        "TEMP1": "None (Default)",
        "ING2": "Rosemary",
        "TEMP2": "None (Default)",
        "ING3": "Guggul",
        "TEMP3": "None (Default)",
        "SYMP1": "weight gain",
        "SYMP2": "hair loss",
        "COMP": ""
    },
    {
        "NAME": "Irritable Bowel Syndrome",
        "ICON": "",
        "TIER": 3,
        "DES": "",
        "ING1": "Slippery Elm",
        "TEMP1": "Cold",
        "ING2": "Flax Seeds",
        "TEMP2": "Hot",
        "ING3": "Marshmallow Root",
        "TEMP3": "None (Default)",
        "SYMP1": "gas",
        "SYMP2": "bloating",
        "COMP": ""
    },
    {
        "NAME": "Lupus",
        "ICON": "",
        "TIER": 3,
        "DES": "",
        "ING1": "Ginseng",
        "TEMP1": "Hot",
        "ING2": "Ashwagandha",
        "TEMP2": "None (Default)",
        "ING3": "Licorice Root",
        "TEMP3": "Cold",
        "SYMP1": "lack of energy",
        "SYMP2": "rash",
        "COMP": ""
    },
    {
        "NAME": "Rheumatoid Arthritis",
        "ICON": "",
        "TIER": 3,
        "DES": "",
        "ING1": "Boswellia",
        "TEMP1": "Hot",
        "ING2": "Alfalfa",
        "TEMP2": "None (Default)",
        "ING3": "Arnica",
        "TEMP3": "None (Default)",
        "SYMP1": "joint pain",
        "SYMP2": "stiff joints",
        "COMP": ""
    },
    {
        "NAME": "Shingles",
        "ICON": "",
        "TIER": 3,
        "DES": "",
        "ING1": "Lemon Balm",
        "TEMP1": "None (Default)",
        "ING2": "Tea Tree Oil",
        "TEMP2": "Hot",
        "ING3": "Jojoba Oil",
        "TEMP3": "Cold",
        "SYMP1": "cysts",
        "SYMP2": "itchy skin",
        "COMP": ""
    },
    {
        "NAME": "Wound Infection",
        "ICON": "",
        "TIER": 3,
        "DES": "",
        "ING1": "Honey",
        "TEMP1": "Hot",
        "ING2": "Dandelion",
        "TEMP2": "Hot",
        "ING3": "Elderberry",
        "TEMP3": "None (Default)",
        "SYMP1": "swelling",
        "SYMP2": "fever and chills",
        "COMP": ""
    },
    {
        "NAME": "Broken Bones",
        "ICON": "",
        "TIER": 3,
        "DES": "",
        "ING1": "Turmeric",
        "TEMP1": "Hot",
        "ING2": "Pomegranate",
        "TEMP2": "None (Default)",
        "ING3": "Red Clover",
        "TEMP3": "None (Default)",
        "SYMP1": "intense pain",
        "SYMP2": "bruising",
        "COMP": ""
    },
    {
        "NAME": "Bell's Palsy",
        "ICON": "",
        "TIER": 4,
        "DES": "",
        "ING1": "Peppermint",
        "TEMP1": "Cold",
        "ING2": "Skullcap",
        "TEMP2": "Cold",
        "ING3": "Lavender",
        "TEMP3": "None (Default)",
        "SYMP1": "muscle paralysis",
        "SYMP2": "headache",
        "COMP": ""
    },
    {
        "NAME": "Crohn's Disease",
        "ICON": "",
        "TIER": 4,
        "DES": "",
        "ING1": "Slippery Elm",
        "TEMP1": "Hot",
        "ING2": "Marshmallow Root",
        "TEMP2": "None (Default)",
        "ING3": "Ashwagandha",
        "TEMP3": "Cold",
        "SYMP1": "gas",
        "SYMP2": "lack of energy",
        "COMP": ""
    },
    {
        "NAME": "Endometriosis",
        "ICON": "",
        "TIER": 4,
        "DES": "",
        "ING1": "Dong Quai",
        "TEMP1": "None (Default)",
        "ING2": "Cinnamon",
        "TEMP2": "Cold",
        "ING3": "Licorice Root",
        "TEMP3": "Hot",
        "SYMP1": "pelvic pain",
        "SYMP2": "nausea",
        "COMP": ""
    },
    {
        "NAME": "Epilepsy",
        "ICON": "",
        "TIER": 4,
        "DES": "",
        "ING1": "Passionflower",
        "TEMP1": "Cold",
        "ING2": "Skullcap",
        "TEMP2": "Hot",
        "ING3": "Valerian",
        "TEMP3": "None (Default)",
        "SYMP1": "seizures",
        "SYMP2": "confusion",
        "COMP": ""
    },
    {
        "NAME": "Hepatitis",
        "ICON": "",
        "TIER": 4,
        "DES": "",
        "ING1": "Milk Thistle",
        "TEMP1": "None (Default)",
        "ING2": "Slippery Elm",
        "TEMP2": "Hot",
        "ING3": "Turmeric",
        "TEMP3": "Cold",
        "SYMP1": "abdominal pain",
        "SYMP2": "jaundice",
        "COMP": ""
    },
    {
        "NAME": "Lyme Disease",
        "ICON": "",
        "TIER": 4,
        "DES": "",
        "ING1": "Fenugreek",
        "TEMP1": "Hot",
        "ING2": "Hawthorn",
        "TEMP2": "Cold",
        "ING3": "Motherwort",
        "TEMP3": "None (Default)",
        "SYMP1": "fever and chills",
        "SYMP2": "irregular heartbeat",
        "COMP": ""
    },
    {
        "NAME": "Multiple Sclerosis",
        "ICON": "",
        "TIER": 4,
        "DES": "",
        "ING1": "Green Tea",
        "TEMP1": "Cold",
        "ING2": "Cherry",
        "TEMP2": "None (Default)",
        "ING3": "Licorice Root",
        "TEMP3": "Hot",
        "SYMP1": "blurred vision",
        "SYMP2": "muscle spasms",
        "COMP": ""
    },
    {
        "NAME": "Hypomagnesemia",
        "ICON": "",
        "TIER": 4,
        "DES": "",
        "ING1": "Milk Thistle",
        "TEMP1": "None (Default)",
        "ING2": "Spinach",
        "TEMP2": "Cold",
        "ING3": "Magnesium",
        "TEMP3": "Hot",
        "SYMP1": "muscle spasms",
        "SYMP2": "weak muscles",
        "COMP": ""
    },
    {
        "NAME": "Parkinson's Disease",
        "ICON": "",
        "TIER": 4,
        "DES": "",
        "ING1": "Velvet Bean",
        "TEMP1": "Hot",
        "ING2": "Lavender",
        "TEMP2": "Cold",
        "ING3": "Bacopa",
        "TEMP3": "None (Default)",
        "SYMP1": "shakiness",
        "SYMP2": "stiff muscles",
        "COMP": ""
    },
    {
        "NAME": "Poisoning",
        "ICON": "",
        "TIER": 4,
        "DES": "",
        "ING1": "Charcoal",
        "TEMP1": "None (Default)",
        "ING2": "Slippery Elm",
        "TEMP2": "Hot",
        "ING3": "Salt",
        "TEMP3": "Cold",
        "SYMP1": "abdominal pain",
        "SYMP2": "vomiting",
        "COMP": ""
    },
    {
        "NAME": "Stunted Growth",
        "ICON": "",
        "TIER": 4,
        "DES": "",
        "ING1": "Prunes",
        "TEMP1": "Hot",
        "ING2": "Bugleweed",
        "TEMP2": "Cold",
        "ING3": "Fish Oil",
        "TEMP3": "None (Default)",
        "SYMP1": "weight loss",
        "SYMP2": "cognitive development",
        "COMP": ""
    },
    {
        "NAME": "Tuberculosis",
        "ICON": "",
        "TIER": 4,
        "DES": "",
        "ING1": "Echinacea",
        "TEMP1": "Hot",
        "ING2": "Garlic",
        "TEMP2": "None (Default)",
        "ING3": "Red Clover",
        "TEMP3": "Cold",
        "SYMP1": "cough",
        "SYMP2": "chest pain",
        "COMP": ""
    },
    {
        "NAME": "Hypoproteinemia",
        "ICON": "",
        "TIER": 4,
        "DES": "",
        "ING1": "Alfalfa",
        "TEMP1": "None (Default)",
        "ING2": "Nettle",
        "TEMP2": "Hot",
        "ING3": "Rosemary",
        "TEMP3": "Cold",
        "SYMP1": "swelling",
        "SYMP2": "hair loss",
        "COMP": ""
    }
]